artificialvision/__init__.py
artificialvision/Integration/ObjDetection.py
artificialvision/utils/EnumClass.py
artificialvision/utils/utils.py
artificialvision/utils/Evaluation/Eval_ObjDetection.py
artificialvision/utils/Inference/Infer_ObjDetection.py
ArtificialVision-0.1.4.dist-info/LICENSE
ArtificialVision-0.1.4.dist-info/METADATA
ArtificialVision-0.1.4.dist-info/WHEEL
ArtificialVision-0.1.4.dist-info/top_level.txt
ArtificialVision-0.1.4.dist-info/RECORD
