Metadata-Version: 2.1
Name: ArtificialVision
Version: 0.1.4
Summary: Artificial Vision Library
Author-email: hwk06023 <hwk06023@gmail.com>
License: Copyright (c) 2012-2024 Scott Chacon and others
Project-URL: Source, https://github.com/hwk06023/ArtificialVision
Keywords: hwk060023,Vision,AI,ML,DL,CV,ArtificialVision,ArtificialIntelligence,MachineLearning,DeepLearning,ComputerVision,Python,PyPI,Package,Tutorial,Research,Development,Library,Framework,Tool,Utility,Module,Class,Function,Method,Variable,Constant,Parameter,Argument,Hyperparameter,Model,Dataset,Preprocessing,Augmentation,Training,Validation,Testing,Evaluation,Prediction,Inference,Analysis,Visualization,Benchmark,Comparison,Documentation,Reference,Paper
Classifier: Programming Language :: Python :: 3
Classifier: License :: OSI Approved :: MIT License
Requires-Python: >=3.9
License-File: LICENSE
Requires-Dist: torch
Requires-Dist: torchvision
Requires-Dist: tensorflow
Requires-Dist: opencv-python
Requires-Dist: scikit-learn
Requires-Dist: numpy
Requires-Dist: scipy
Requires-Dist: matplotlib
Requires-Dist: tqdm
Requires-Dist: pillow
